llmada/__init__.py
llmada/client.py
llmada/core.py
llmada/log.py
llmada/utils.py
llmada/protocols/__init__.py
llmada/protocols/protocols.py
llmada-1.1.12.dist-info/METADATA
llmada-1.1.12.dist-info/WHEEL
llmada-1.1.12.dist-info/top_level.txt
llmada-1.1.12.dist-info/RECORD
