Metadata-Version: 2.4
Name: llmada
Version: 1.1.12
Summary: 提升了系统
Requires-Python: >=3.10
Requires-Dist: cryptography>=45.0.4
Requires-Dist: google-genai>=1.13.0
Requires-Dist: llama-index>=0.12.30
Requires-Dist: openai>=1.70.0
Requires-Dist: python-dotenv>=1.1.0
Requires-Dist: sse-starlette>=2.3.3
Requires-Dist: httpx[http2]>=0.28.1
Requires-Dist: fastapi>=0.115.12
Requires-Dist: volcengine-python-sdk==4.0.6
Requires-Dist: toml==0.10.2
Requires-Dist: anyio>=4.9.0
Requires-Dist: uvicorn>=0.35.0
Requires-Dist: tenacity>=8.5.0
Requires-Dist: pytest>=8.4.2
Requires-Dist: pytest-tornasync>=0.6.0.post2
Requires-Dist: pytest-asyncio>=1.2.0
